{"name":"manageBankAccountUsingGVAGLBankAccount","id":"org.icrc.fadapplic.IRIS.FAD.AccountsPayable.ManageBankAccount:manageBankAccountUsingGVAGLBankAccount","testCaseName":"org.icrc.fadapplic.IRIS.FAD.AccountsPayable.ManageBankAccount","testSteps":[{"number":1,"description":"Given that im logged into manage bank account page","duration":31778,"startTime":"2024-05-30T11:29:46.696+08:00[Asia/Shanghai]","screenshots":[{"screenshot":"3ff3537d6b424778b967483a2289486f2a9fb0d872d7857e583b7dbd9ed1dd2b.png","timeStamp":1717039818473}],"result":"SUCCESS","precondition":false,"level":0,"children":[{"number":2,"description":"When i open FAD URL","duration":27551,"startTime":"2024-05-30T11:29:46.697+08:00[Asia/Shanghai]","screenshots":[{"screenshot":"5ac754d6ca115aecd06ab20d3a3e88191bd7f8c525ef6deb71c7a98c957197cf.png","timeStamp":1717039814247}],"result":"SUCCESS","precondition":false,"level":1},{"number":3,"description":"When i open page from sidebar menu: {Supplier Management,Manage Bank Account}","duration":4218,"startTime":"2024-05-30T11:30:14.249+08:00[Asia/Shanghai]","screenshots":[{"screenshot":"5ac754d6ca115aecd06ab20d3a3e88191bd7f8c525ef6deb71c7a98c957197cf.png","timeStamp":1717039814256},{"screenshot":"8e449641b690de74bd723b072a07128fdebe01a02087583054a87ff120ffc5ba.png","timeStamp":1717039814806},{"screenshot":"4c3dd41d42cedbfd446e2b3bb18e431a49ef78d17e4d178f69906798f2c700da.png","timeStamp":1717039815288},{"screenshot":"3ff3537d6b424778b967483a2289486f2a9fb0d872d7857e583b7dbd9ed1dd2b.png","timeStamp":1717039818467}],"result":"SUCCESS","precondition":false,"level":1}]},{"number":4,"description":"Then the manage bank account page and its contents should show up","duration":223,"startTime":"2024-05-30T11:30:18.474+08:00[Asia/Shanghai]","screenshots":[{"screenshot":"3ff3537d6b424778b967483a2289486f2a9fb0d872d7857e583b7dbd9ed1dd2b.png","timeStamp":1717039818697}],"result":"SUCCESS","precondition":false,"level":0},{"number":5,"description":"When I set the \u0027Supplier\u0027 to \u002754556\u0027","duration":3051,"startTime":"2024-05-30T11:30:18.698+08:00[Asia/Shanghai]","screenshots":[{"screenshot":"b3d1db6e259747498f9b8a16fd1007126061a09be57a86e98d5e1a56b9fde61c.png","timeStamp":1717039820667},{"screenshot":"1650c632066bb3c994799e50a4857755a8e3b7c7ced590f8c960ff03e0f6ea61.png","timeStamp":1717039821749}],"result":"SUCCESS","precondition":false,"level":0},{"number":6,"description":"When i click search button","duration":1202,"startTime":"2024-05-30T11:30:21.750+08:00[Asia/Shanghai]","screenshots":[{"screenshot":"cee58fdf0f4982d1a4e318c299f7305a0abc45226956bcd824c83de9dcd826b3.png","timeStamp":1717039822238},{"screenshot":"e7b014f12e71864618401ab386530787eaca6085c12e1d12f5dd9e9ea1884805.png","timeStamp":1717039822951}],"result":"SUCCESS","precondition":false,"level":0},{"number":7,"description":"Then a search result should show up","duration":381,"startTime":"2024-05-30T11:30:22.953+08:00[Asia/Shanghai]","screenshots":[{"screenshot":"3347570eb979d55ebbddcf413c2373401da8265255a6e36ee7b2a2486be4c667.png","timeStamp":1717039823334}],"result":"SUCCESS","precondition":false,"level":0},{"number":8,"description":"Then the bank account number of the first supplier bank account should have a value","duration":416,"startTime":"2024-05-30T11:30:23.335+08:00[Asia/Shanghai]","screenshots":[{"screenshot":"e36a62ec2ff52947c8670a361941ab98999ccd27cf661a54dcd3fac44746d5d8.png","timeStamp":1717039823751}],"result":"SUCCESS","precondition":false,"level":0},{"number":9,"description":"When i save the bank account number of the first bank account from search result","duration":433,"startTime":"2024-05-30T11:30:23.752+08:00[Asia/Shanghai]","screenshots":[{"screenshot":"e36a62ec2ff52947c8670a361941ab98999ccd27cf661a54dcd3fac44746d5d8.png","timeStamp":1717039824185}],"result":"SUCCESS","precondition":false,"level":0},{"number":10,"description":"When i click on edit button of the first supplier bank account","duration":3868,"startTime":"2024-05-30T11:30:24.186+08:00[Asia/Shanghai]","screenshots":[{"screenshot":"a79bbbe8f9d69952098b89715f9afd12d1b5eba0efc12dfd0b2e5c9ac791f31e.png","timeStamp":1717039824835},{"screenshot":"4381eb980094d5096ae3023f0662b7dc37cb4ee3ff499b63473f95677bc7290a.png","timeStamp":1717039828054}],"result":"SUCCESS","precondition":false,"level":0},{"number":11,"description":"Then the add bank account form should show up","duration":239,"startTime":"2024-05-30T11:30:28.055+08:00[Asia/Shanghai]","screenshots":[{"screenshot":"4381eb980094d5096ae3023f0662b7dc37cb4ee3ff499b63473f95677bc7290a.png","htmlSource":"pagesource9099807013917679556.html.txt","timeStamp":1717039828292}],"exception":{"errorType":"java.lang.AssertionError","stackTrace":[{"declaringClass":"steps.IRIS.FAD.ManageBankAccountSteps","methodName":"then_the_Add_Bank_Account_form_should_show_up","fileName":"ManageBankAccountSteps.java","lineNumber":54},{"declaringClass":"org.icrc.fadapplic.IRIS.FAD.AccountsPayable.ManageBankAccount","methodName":"manageBankAccountUsingGVAGLBankAccount","fileName":"ManageBankAccount.java","lineNumber":78}]},"result":"FAILURE","precondition":false,"level":0},{"number":12,"description":"Then the internal information accordion form should be opened","duration":0,"startTime":"2024-05-30T11:30:28.300+08:00[Asia/Shanghai]","result":"SKIPPED","precondition":false,"level":0},{"number":13,"description":"When I set the \u0027GL Bank Account\u0027 to \u00271GVA400.410001\u0027","duration":1,"startTime":"2024-05-30T11:30:28.306+08:00[Asia/Shanghai]","result":"SKIPPED","precondition":false,"level":0},{"number":14,"description":"When i click accordion continue button","duration":0,"startTime":"2024-05-30T11:30:28.313+08:00[Asia/Shanghai]","result":"SKIPPED","precondition":false,"level":0},{"number":15,"description":"Then the beneficiary bank accordion form should be opened","duration":1,"startTime":"2024-05-30T11:30:28.318+08:00[Asia/Shanghai]","result":"SKIPPED","precondition":false,"level":0},{"number":16,"description":"When I set the \u0027Swift Code\u0027 to \u0027AUBKPHMM\u0027","duration":0,"startTime":"2024-05-30T11:30:28.326+08:00[Asia/Shanghai]","result":"SKIPPED","precondition":false,"level":0},{"number":17,"description":"When i click on validate button","duration":1,"startTime":"2024-05-30T11:30:28.333+08:00[Asia/Shanghai]","result":"SKIPPED","precondition":false,"level":0},{"number":18,"description":"When I set the \u0027Bank Name\u0027 to \u0027Edited Bank Account Test Name\u0027","duration":1,"startTime":"2024-05-30T11:30:28.339+08:00[Asia/Shanghai]","result":"SKIPPED","precondition":false,"level":0},{"number":19,"description":"When I set the \u0027Currency\u0027 to \u0027USD\u0027","duration":0,"startTime":"2024-05-30T11:30:28.346+08:00[Asia/Shanghai]","result":"SKIPPED","precondition":false,"level":0},{"number":20,"description":"When I set the \u0027Customer Bank Account\u0027 to \u00270917424199\u0027","duration":0,"startTime":"2024-05-30T11:30:28.352+08:00[Asia/Shanghai]","result":"SKIPPED","precondition":false,"level":0},{"number":21,"description":"When I set the \u0027Bank Address\u0027 to \u0027Makati\u0027","duration":0,"startTime":"2024-05-30T11:30:28.358+08:00[Asia/Shanghai]","result":"SKIPPED","precondition":false,"level":0},{"number":22,"description":"When I set the \u0027City\u0027 to \u0027Makati\u0027","duration":1,"startTime":"2024-05-30T11:30:28.363+08:00[Asia/Shanghai]","result":"SKIPPED","precondition":false,"level":0},{"number":23,"description":"When I set the \u0027Country\u0027 to \u0027Philippines\u0027","duration":1,"startTime":"2024-05-30T11:30:28.370+08:00[Asia/Shanghai]","result":"SKIPPED","precondition":false,"level":0},{"number":24,"description":"When i click accordion continue button","duration":1,"startTime":"2024-05-30T11:30:28.378+08:00[Asia/Shanghai]","result":"SKIPPED","precondition":false,"level":0},{"number":25,"description":"Then the payment instructions accordion form should be opened","duration":0,"startTime":"2024-05-30T11:30:28.385+08:00[Asia/Shanghai]","result":"SKIPPED","precondition":false,"level":0},{"number":26,"description":"When i click save button","duration":0,"startTime":"2024-05-30T11:30:28.391+08:00[Asia/Shanghai]","result":"SKIPPED","precondition":false,"level":0},{"number":27,"description":"Then the bank account edited successfully notification should show up","duration":0,"startTime":"2024-05-30T11:30:28.397+08:00[Asia/Shanghai]","result":"SKIPPED","precondition":false,"level":0},{"number":28,"description":"When I set the Bank Account Number to \u00270917424199\u0027","duration":1,"startTime":"2024-05-30T11:30:28.402+08:00[Asia/Shanghai]","result":"SKIPPED","precondition":false,"level":0},{"number":29,"description":"When i click search button","duration":0,"startTime":"2024-05-30T11:30:28.411+08:00[Asia/Shanghai]","result":"SKIPPED","precondition":false,"level":0},{"number":30,"description":"When i click on edit button of the first supplier bank account","duration":0,"startTime":"2024-05-30T11:30:28.420+08:00[Asia/Shanghai]","result":"SKIPPED","precondition":false,"level":0},{"number":31,"description":"Then the add bank account form should show up","duration":1,"startTime":"2024-05-30T11:30:28.428+08:00[Asia/Shanghai]","result":"SKIPPED","precondition":false,"level":0},{"number":32,"description":"Then the internal information accordion form should be opened","duration":0,"startTime":"2024-05-30T11:30:28.437+08:00[Asia/Shanghai]","result":"SKIPPED","precondition":false,"level":0},{"number":33,"description":"When I set the \u0027GL Bank Account\u0027 to \u00271GVA400.410002\u0027","duration":0,"startTime":"2024-05-30T11:30:28.445+08:00[Asia/Shanghai]","result":"SKIPPED","precondition":false,"level":0},{"number":34,"description":"When i click accordion continue button","duration":1,"startTime":"2024-05-30T11:30:28.452+08:00[Asia/Shanghai]","result":"SKIPPED","precondition":false,"level":0},{"number":35,"description":"Then the beneficiary bank accordion form should be opened","duration":0,"startTime":"2024-05-30T11:30:28.459+08:00[Asia/Shanghai]","result":"SKIPPED","precondition":false,"level":0},{"number":36,"description":"When I set the \u0027Swift Code\u0027 to \u0027AUBKPHMM\u0027","duration":1,"startTime":"2024-05-30T11:30:28.465+08:00[Asia/Shanghai]","result":"SKIPPED","precondition":false,"level":0},{"number":37,"description":"When i click on validate button","duration":0,"startTime":"2024-05-30T11:30:28.472+08:00[Asia/Shanghai]","result":"SKIPPED","precondition":false,"level":0},{"number":38,"description":"When I set the \u0027Bank Name\u0027 to \u0027Edited Bank Account Test Name\u0027","duration":0,"startTime":"2024-05-30T11:30:28.478+08:00[Asia/Shanghai]","result":"SKIPPED","precondition":false,"level":0},{"number":39,"description":"When I set the \u0027Currency\u0027 to \u0027USD\u0027","duration":0,"startTime":"2024-05-30T11:30:28.486+08:00[Asia/Shanghai]","result":"SKIPPED","precondition":false,"level":0},{"number":40,"description":"When I set the \u0027Customer Bank Account\u0027 to \u00270917424199\u0027","duration":0,"startTime":"2024-05-30T11:30:28.492+08:00[Asia/Shanghai]","result":"SKIPPED","precondition":false,"level":0},{"number":41,"description":"When I set the \u0027Bank Address\u0027 to \u0027Makati\u0027","duration":0,"startTime":"2024-05-30T11:30:28.498+08:00[Asia/Shanghai]","result":"SKIPPED","precondition":false,"level":0},{"number":42,"description":"When I set the \u0027City\u0027 to \u0027Makati\u0027","duration":1,"startTime":"2024-05-30T11:30:28.503+08:00[Asia/Shanghai]","result":"SKIPPED","precondition":false,"level":0},{"number":43,"description":"When I set the \u0027Country\u0027 to \u0027Philippines\u0027","duration":0,"startTime":"2024-05-30T11:30:28.509+08:00[Asia/Shanghai]","result":"SKIPPED","precondition":false,"level":0},{"number":44,"description":"When i click accordion continue button","duration":0,"startTime":"2024-05-30T11:30:28.515+08:00[Asia/Shanghai]","result":"SKIPPED","precondition":false,"level":0},{"number":45,"description":"Then the payment instructions accordion form should be opened","duration":1,"startTime":"2024-05-30T11:30:28.520+08:00[Asia/Shanghai]","result":"SKIPPED","precondition":false,"level":0},{"number":46,"description":"When i click save button","duration":1,"startTime":"2024-05-30T11:30:28.526+08:00[Asia/Shanghai]","result":"SKIPPED","precondition":false,"level":0},{"number":47,"description":"Then the bank account edited successfully notification should show up","duration":1,"startTime":"2024-05-30T11:30:28.534+08:00[Asia/Shanghai]","result":"SKIPPED","precondition":false,"level":0},{"number":48,"description":"When I set the Bank Account Number to \u00270917424199\u0027","duration":0,"startTime":"2024-05-30T11:30:28.543+08:00[Asia/Shanghai]","result":"SKIPPED","precondition":false,"level":0},{"number":49,"description":"When i click search button","duration":0,"startTime":"2024-05-30T11:30:28.549+08:00[Asia/Shanghai]","result":"SKIPPED","precondition":false,"level":0},{"number":50,"description":"When i click on edit button of the first supplier bank account","duration":0,"startTime":"2024-05-30T11:30:28.554+08:00[Asia/Shanghai]","result":"SKIPPED","precondition":false,"level":0},{"number":51,"description":"Then the add bank account form should show up","duration":1,"startTime":"2024-05-30T11:30:28.559+08:00[Asia/Shanghai]","result":"SKIPPED","precondition":false,"level":0},{"number":52,"description":"Then the internal information accordion form should be opened","duration":0,"startTime":"2024-05-30T11:30:28.566+08:00[Asia/Shanghai]","result":"SKIPPED","precondition":false,"level":0},{"number":53,"description":"When I set the \u0027GL Bank Account\u0027 to \u00271GVA400.410003\u0027","duration":1,"startTime":"2024-05-30T11:30:28.572+08:00[Asia/Shanghai]","result":"SKIPPED","precondition":false,"level":0},{"number":54,"description":"When i click accordion continue button","duration":1,"startTime":"2024-05-30T11:30:28.579+08:00[Asia/Shanghai]","result":"SKIPPED","precondition":false,"level":0},{"number":55,"description":"Then the beneficiary bank accordion form should be opened","duration":1,"startTime":"2024-05-30T11:30:28.585+08:00[Asia/Shanghai]","result":"SKIPPED","precondition":false,"level":0},{"number":56,"description":"When I set the \u0027Swift Code\u0027 to \u0027AUBKPHMM\u0027","duration":0,"startTime":"2024-05-30T11:30:28.592+08:00[Asia/Shanghai]","result":"SKIPPED","precondition":false,"level":0},{"number":57,"description":"When i click on validate button","duration":0,"startTime":"2024-05-30T11:30:28.600+08:00[Asia/Shanghai]","result":"SKIPPED","precondition":false,"level":0},{"number":58,"description":"When I set the \u0027Bank Name\u0027 to \u0027Edited Bank Account Test Name\u0027","duration":0,"startTime":"2024-05-30T11:30:28.606+08:00[Asia/Shanghai]","result":"SKIPPED","precondition":false,"level":0},{"number":59,"description":"When I set the \u0027Currency\u0027 to \u0027USD\u0027","duration":0,"startTime":"2024-05-30T11:30:28.612+08:00[Asia/Shanghai]","result":"SKIPPED","precondition":false,"level":0},{"number":60,"description":"When I set the \u0027Customer Bank Account\u0027 to \u00270917424199\u0027","duration":1,"startTime":"2024-05-30T11:30:28.617+08:00[Asia/Shanghai]","result":"SKIPPED","precondition":false,"level":0},{"number":61,"description":"When I set the \u0027Bank Address\u0027 to \u0027Makati\u0027","duration":1,"startTime":"2024-05-30T11:30:28.623+08:00[Asia/Shanghai]","result":"SKIPPED","precondition":false,"level":0},{"number":62,"description":"When I set the \u0027City\u0027 to \u0027Makati\u0027","duration":0,"startTime":"2024-05-30T11:30:28.632+08:00[Asia/Shanghai]","result":"SKIPPED","precondition":false,"level":0},{"number":63,"description":"When I set the \u0027Country\u0027 to \u0027Philippines\u0027","duration":0,"startTime":"2024-05-30T11:30:28.639+08:00[Asia/Shanghai]","result":"SKIPPED","precondition":false,"level":0},{"number":64,"description":"When i click accordion continue button","duration":0,"startTime":"2024-05-30T11:30:28.645+08:00[Asia/Shanghai]","result":"SKIPPED","precondition":false,"level":0},{"number":65,"description":"Then the payment instructions accordion form should be opened","duration":1,"startTime":"2024-05-30T11:30:28.650+08:00[Asia/Shanghai]","result":"SKIPPED","precondition":false,"level":0},{"number":66,"description":"When i click save button","duration":0,"startTime":"2024-05-30T11:30:28.656+08:00[Asia/Shanghai]","result":"SKIPPED","precondition":false,"level":0},{"number":67,"description":"Then the bank account edited successfully notification should show up","duration":1,"startTime":"2024-05-30T11:30:28.661+08:00[Asia/Shanghai]","result":"SKIPPED","precondition":false,"level":0},{"number":68,"description":"When I set the Bank Account Number to \u00270917424199\u0027","duration":0,"startTime":"2024-05-30T11:30:28.668+08:00[Asia/Shanghai]","result":"SKIPPED","precondition":false,"level":0},{"number":69,"description":"When i click search button","duration":1,"startTime":"2024-05-30T11:30:28.673+08:00[Asia/Shanghai]","result":"SKIPPED","precondition":false,"level":0},{"number":70,"description":"When i click on edit button of the first supplier bank account","duration":0,"startTime":"2024-05-30T11:30:28.679+08:00[Asia/Shanghai]","result":"SKIPPED","precondition":false,"level":0},{"number":71,"description":"Then the add bank account form should show up","duration":0,"startTime":"2024-05-30T11:30:28.685+08:00[Asia/Shanghai]","result":"SKIPPED","precondition":false,"level":0},{"number":72,"description":"Then the internal information accordion form should be opened","duration":0,"startTime":"2024-05-30T11:30:28.690+08:00[Asia/Shanghai]","result":"SKIPPED","precondition":false,"level":0},{"number":73,"description":"When I set the \u0027GL Bank Account\u0027 to \u00271GVA400.410004\u0027","duration":0,"startTime":"2024-05-30T11:30:28.695+08:00[Asia/Shanghai]","result":"SKIPPED","precondition":false,"level":0},{"number":74,"description":"When i click accordion continue button","duration":0,"startTime":"2024-05-30T11:30:28.702+08:00[Asia/Shanghai]","result":"SKIPPED","precondition":false,"level":0},{"number":75,"description":"Then the beneficiary bank accordion form should be opened","duration":0,"startTime":"2024-05-30T11:30:28.710+08:00[Asia/Shanghai]","result":"SKIPPED","precondition":false,"level":0},{"number":76,"description":"When I set the \u0027Swift Code\u0027 to \u0027AUBKPHMM\u0027","duration":0,"startTime":"2024-05-30T11:30:28.717+08:00[Asia/Shanghai]","result":"SKIPPED","precondition":false,"level":0},{"number":77,"description":"When i click on validate button","duration":1,"startTime":"2024-05-30T11:30:28.722+08:00[Asia/Shanghai]","result":"SKIPPED","precondition":false,"level":0},{"number":78,"description":"When I set the \u0027Bank Name\u0027 to \u0027Edited Bank Account Test Name\u0027","duration":0,"startTime":"2024-05-30T11:30:28.728+08:00[Asia/Shanghai]","result":"SKIPPED","precondition":false,"level":0},{"number":79,"description":"When I set the \u0027Currency\u0027 to \u0027USD\u0027","duration":0,"startTime":"2024-05-30T11:30:28.736+08:00[Asia/Shanghai]","result":"SKIPPED","precondition":false,"level":0},{"number":80,"description":"When I set the \u0027Customer Bank Account\u0027 to \u00270917424199\u0027","duration":0,"startTime":"2024-05-30T11:30:28.743+08:00[Asia/Shanghai]","result":"SKIPPED","precondition":false,"level":0},{"number":81,"description":"When I set the \u0027Bank Address\u0027 to \u0027Makati\u0027","duration":0,"startTime":"2024-05-30T11:30:28.749+08:00[Asia/Shanghai]","result":"SKIPPED","precondition":false,"level":0},{"number":82,"description":"When I set the \u0027City\u0027 to \u0027Makati\u0027","duration":1,"startTime":"2024-05-30T11:30:28.754+08:00[Asia/Shanghai]","result":"SKIPPED","precondition":false,"level":0},{"number":83,"description":"When I set the \u0027Country\u0027 to \u0027Philippines\u0027","duration":0,"startTime":"2024-05-30T11:30:28.760+08:00[Asia/Shanghai]","result":"SKIPPED","precondition":false,"level":0},{"number":84,"description":"When i click accordion continue button","duration":0,"startTime":"2024-05-30T11:30:28.765+08:00[Asia/Shanghai]","result":"SKIPPED","precondition":false,"level":0},{"number":85,"description":"Then the payment instructions accordion form should be opened","duration":1,"startTime":"2024-05-30T11:30:28.770+08:00[Asia/Shanghai]","result":"SKIPPED","precondition":false,"level":0},{"number":86,"description":"When i click save button","duration":0,"startTime":"2024-05-30T11:30:28.776+08:00[Asia/Shanghai]","result":"SKIPPED","precondition":false,"level":0},{"number":87,"description":"Then the bank account edited successfully notification should show up","duration":1,"startTime":"2024-05-30T11:30:28.781+08:00[Asia/Shanghai]","result":"SKIPPED","precondition":false,"level":0}],"userStory":{"id":"org.icrc.fadapplic.IRIS.FAD.AccountsPayable.ManageBankAccount","storyName":"Manage bank account","storyClassName":"org.icrc.fadapplic.IRIS.FAD.AccountsPayable.ManageBankAccount","path":"FAD.AccountsPayable","type":"story"},"featureTag":{"name":"Accounts payable/Manage bank account","type":"story","displayName":"Accounts payable/Manage bank account"},"title":"Manage bank account using GVAGL bank account","coreIssues":["SPRINT7"],"tags":[{"name":"FAD/Accounts payable","type":"feature","displayName":"Accounts payable"},{"name":"FAD","type":"capability","displayName":"FAD"},{"name":"Accounts payable/Manage bank account","type":"story","displayName":"Accounts payable/Manage bank account"}],"startTime":"2024-05-30T11:29:46.465+08:00[Asia/Shanghai]","duration":42318,"testFailureCause":{"errorType":"java.lang.AssertionError","stackTrace":[{"declaringClass":"steps.IRIS.FAD.ManageBankAccountSteps","methodName":"then_the_Add_Bank_Account_form_should_show_up","fileName":"ManageBankAccountSteps.java","lineNumber":54},{"declaringClass":"org.icrc.fadapplic.IRIS.FAD.AccountsPayable.ManageBankAccount","methodName":"manageBankAccountUsingGVAGLBankAccount","fileName":"ManageBankAccount.java","lineNumber":78}]},"testFailureClassname":"java.lang.AssertionError","testFailureSummary":"FAILURE;java.lang.AssertionError;null;ManageBankAccountSteps.java","projectKey":"","annotatedResult":"FAILURE","sessionId":"92226aebb7b4440ad186165bc87b243e","driver":"chrome","isManualTestingUpToDate":false,"manual":false,"testSource":"JUnit","result":"FAILURE","issues":["SPRINT7"]}